archetypax/__init__.py
archetypax/logger/__init__.py
archetypax/logger/core.py
archetypax/logger/messages.py
archetypax/logger/examples/logger_usage.py
archetypax/logger/examples/refactoring_guide.py
archetypax/models/__init__.py
archetypax/models/archetypes.py
archetypax/models/base.py
archetypax/models/biarchetypes.py
archetypax/models/sparse_archetypes.py
archetypax/tools/__init__.py
archetypax/tools/evaluation.py
archetypax/tools/interpret.py
archetypax/tools/tracker.py
archetypax/tools/visualization.py
archetypax-0.1.2.dist-info/licenses/LICENSE
archetypax-0.1.2.dist-info/METADATA
archetypax-0.1.2.dist-info/WHEEL
archetypax-0.1.2.dist-info/top_level.txt
archetypax-0.1.2.dist-info/RECORD
