Metadata-Version: 2.4
Name: archetypax
Version: 0.1.2
Summary: GPU-accelerated Archetypal Analysis implementation using JAX
Author-email: mary <mary.lv416e@gmail.com>
License: Apache-2.0
Classifier: Development Status :: 3 - Alpha
Classifier: Intended Audience :: Science/Research
Classifier: License :: OSI Approved :: Apache Software License
Classifier: Programming Language :: Python :: 3
Classifier: Programming Language :: Python :: 3.10
Classifier: Programming Language :: Python :: 3.11
Classifier: Programming Language :: Python :: 3.12
Classifier: Topic :: Scientific/Engineering
Classifier: Topic :: Scientific/Engineering :: Artificial Intelligence
Requires-Python: >=3.10
License-File: LICENSE
Requires-Dist: jax>=0.4.0
Requires-Dist: numpy>=1.20.0
Requires-Dist: scikit-learn>=1.0.0
Requires-Dist: optax>=0.1.0
Requires-Dist: pandas>=1.3.0
Provides-Extra: dev
Requires-Dist: ruff>=0.9.0; extra == "dev"
Requires-Dist: pytest>=7.0.0; extra == "dev"
Requires-Dist: black==23.7.0; extra == "dev"
Requires-Dist: mypy>=1.8.0; extra == "dev"
Requires-Dist: types-requests; extra == "dev"
Requires-Dist: types-setuptools; extra == "dev"
Requires-Dist: pandas-stubs; extra == "dev"
Provides-Extra: docs
Requires-Dist: sphinx>=7.2.0; extra == "docs"
Requires-Dist: sphinx-rtd-theme>=2.0.0; extra == "docs"
Requires-Dist: sphinx-autodoc-typehints>=1.25.0; extra == "docs"
Requires-Dist: myst-parser>=2.0.0; extra == "docs"
Requires-Dist: nbsphinx>=0.9.0; extra == "docs"
Requires-Dist: matplotlib>=3.7.5; extra == "docs"
Requires-Dist: seaborn>=0.13.2; extra == "docs"
Provides-Extra: examples
Requires-Dist: matplotlib>=3.7.5; extra == "examples"
Requires-Dist: pandas>=1.3.0; extra == "examples"
Requires-Dist: seaborn>=0.13.2; extra == "examples"
Requires-Dist: jupyter>=1.0.0; extra == "examples"
Dynamic: license-file
